{
  "nodes": [
    {
      "x": 245.79638671875,
      "y": 100,
      "text": "TP",
      "features": [],
      "id": "1748631350520s74kduo",
      "style": "none"
    },
    {
      "x": 165.79638671875,
      "y": 160,
      "text": "DP\nJohn",
      "features": [
        "3sg.m",
        "~uCase~:nom"
      ],
      "id": "1748631356602nmmky9s",
      "style": "none"
    },
    {
      "x": 325.79638671875,
      "y": 160,
      "text": "T'",
      "features": [],
      "id": "17486313618647t7vqev",
      "style": "none"
    },
    {
      "x": 265.79638671875,
      "y": 220,
      "text": "T",
      "features": [
        "~EPP~",
        "~uϕ~:3sg",
        "~nom~"
      ],
      "id": "17486313676274x428ll",
      "style": "none"
    },
    {
      "x": 385.79638671875,
      "y": 300,
      "text": "vP",
      "features": [],
      "id": "1748631370763e98734s",
      "style": "none"
    },
    {
      "x": 325.79638671875,
      "y": 360,
      "text": "~DP~\n~John~",
      "features": [],
      "id": "1748631374880acyodr6",
      "style": "none"
    },
    {
      "x": 445.79638671875,
      "y": 360,
      "text": "v'",
      "features": [],
      "id": "1748631385265gkw4yq9",
      "style": "none"
    },
    {
      "x": 385.79638671875,
      "y": 420,
      "text": "kick+v",
      "features": [
        "~acc~",
        "~uV~",
        "~uD~"
      ],
      "id": "17486313915165kln8v7",
      "style": "none"
    },
    {
      "x": 545.79638671875,
      "y": 480,
      "text": "DP",
      "features": [
        "3sg.n",
        "~uCase~:acc"
      ],
      "id": "17486313970100g0svtc",
      "style": "none"
    },
    {
      "x": 505.79638671875,
      "y": 580,
      "text": "D\nthe",
      "features": [
        "~uN~"
      ],
      "id": "1748631400747310hdwv",
      "style": "none"
    },
    {
      "x": 585.79638671875,
      "y": 580,
      "text": "NP\nball",
      "features": [],
      "id": "1748631405124udkfuz8",
      "style": "none"
    },
    {
      "x": 505.79638671875,
      "y": 420,
      "text": "VP",
      "features": [],
      "id": "1748645930650gpkxhep",
      "style": "none"
    },
    {
      "x": 465.79638671875,
      "y": 480,
      "text": "V\n~kick~",
      "features": [
        "~uD~"
      ],
      "id": "1748645937074cucmww1",
      "style": "none"
    },
    {
      "x": 645.79638671875,
      "y": 300,
      "text": "PP",
      "features": [],
      "id": "17486886985857v5vua1",
      "style": "none"
    },
    {
      "x": 605.79638671875,
      "y": 360,
      "text": "P\nin",
      "features": [
        "~acc~"
      ],
      "id": "1748688704513fpucf04",
      "style": "none"
    },
    {
      "x": 685.79638671875,
      "y": 360,
      "text": "DP",
      "features": [
        "~uCase~:acc"
      ],
      "id": "1748688714718mr44x2p",
      "style": "none"
    },
    {
      "x": 645.79638671875,
      "y": 460,
      "text": "D\nthe",
      "features": [
        "~uN~"
      ],
      "id": "1748688726296rqq5obx",
      "style": "none"
    },
    {
      "x": 725.79638671875,
      "y": 460,
      "text": "NP\nfield",
      "features": [],
      "id": "1748688728040j7rzrx1",
      "style": "none"
    },
    {
      "x": 465.79638671875,
      "y": 220,
      "text": "vP",
      "features": [],
      "id": "1748688806367hoyobg5",
      "style": "none"
    }
  ],
  "connections": [
    {
      "fromId": "1748631350520s74kduo",
      "toId": "1748631356602nmmky9s",
      "id": "1748631423069davc3d4"
    },
    {
      "fromId": "1748631350520s74kduo",
      "toId": "17486313618647t7vqev",
      "id": "17486314241565q16ask"
    },
    {
      "fromId": "17486313618647t7vqev",
      "toId": "17486313676274x428ll",
      "id": "1748631429636j85wd7g"
    },
    {
      "fromId": "1748631370763e98734s",
      "toId": "1748631374880acyodr6",
      "id": "1748631433132hhfj3c2"
    },
    {
      "fromId": "1748631370763e98734s",
      "toId": "1748631385265gkw4yq9",
      "id": "17486314343235jwd3mj"
    },
    {
      "fromId": "1748631385265gkw4yq9",
      "toId": "17486313915165kln8v7",
      "id": "1748631435196c9i4kfq"
    },
    {
      "fromId": "17486313970100g0svtc",
      "toId": "1748631400747310hdwv",
      "id": "1748631438778tbjgsei"
    },
    {
      "fromId": "17486313970100g0svtc",
      "toId": "1748631405124udkfuz8",
      "id": "17486314396035fp19mj"
    },
    {
      "fromId": "1748631385265gkw4yq9",
      "toId": "1748645930650gpkxhep",
      "id": "1748645950012qax2hyv"
    },
    {
      "fromId": "1748645930650gpkxhep",
      "toId": "1748645937074cucmww1",
      "id": "174864595469683nuoy6"
    },
    {
      "fromId": "1748645930650gpkxhep",
      "toId": "17486313970100g0svtc",
      "id": "17486459555292b51v9g"
    },
    {
      "fromId": "17486886985857v5vua1",
      "toId": "1748688704513fpucf04",
      "id": "1748688772173eowb4tg"
    },
    {
      "fromId": "17486886985857v5vua1",
      "toId": "1748688714718mr44x2p",
      "id": "1748688773205q4yyba8"
    },
    {
      "fromId": "1748688714718mr44x2p",
      "toId": "1748688726296rqq5obx",
      "id": "1748688774306jf96lc3"
    },
    {
      "fromId": "1748688714718mr44x2p",
      "toId": "1748688728040j7rzrx1",
      "id": "1748688780763o3t56ce"
    },
    {
      "fromId": "1748688806367hoyobg5",
      "toId": "1748631370763e98734s",
      "id": "1748688849223mcomopa"
    },
    {
      "fromId": "1748688806367hoyobg5",
      "toId": "17486886985857v5vua1",
      "id": "1748688853751khomy2q"
    },
    {
      "fromId": "17486313618647t7vqev",
      "toId": "1748688806367hoyobg5",
      "id": "1748688855652kp9kksy"
    }
  ],
  "movementArrows": [
    {
      "fromId": "1748631374880acyodr6",
      "toId": "1748631356602nmmky9s",
      "id": "1748645904474llxd0ktzk",
      "curveDirection": 1,
      "controlPointX": 160,
      "controlPointY": 360
    },
    {
      "fromId": "1748645937074cucmww1",
      "toId": "17486313915165kln8v7",
      "id": "1748688868646s36k0zwtx",
      "curveDirection": -1,
      "controlPointX": 380,
      "controlPointY": 575
    }
  ],
  "settings": {
    "showGrid": true,
    "canvasWidth": 900,
    "canvasHeight": 800
  }
}